bsk_rl/__init__.py
bsk_rl/_default.rst
bsk_rl/finish_install.py
bsk_rl/gym.py
bsk_rl/_dat/world.200407.3x5400x2700.jpg
bsk_rl/_dat/simplemaps_worldcities/license.txt
bsk_rl/_dat/simplemaps_worldcities/worldcities.csv
bsk_rl/_dat/simplemaps_worldcities/worldcities.xlsx
bsk_rl/act/__init__.py
bsk_rl/act/actions.py
bsk_rl/act/continuous_actions.py
bsk_rl/act/discrete_actions.py
bsk_rl/comm/__init__.py
bsk_rl/comm/communication.py
bsk_rl/data/__init__.py
bsk_rl/data/base.py
bsk_rl/data/composition.py
bsk_rl/data/nadir_data.py
bsk_rl/data/no_data.py
bsk_rl/data/resource_data.py
bsk_rl/data/rso_inspection.py
bsk_rl/data/unique_image_data.py
bsk_rl/obs/__init__.py
bsk_rl/obs/observations.py
bsk_rl/obs/relative_observations.py
bsk_rl/sats/__init__.py
bsk_rl/sats/access_satellite.py
bsk_rl/sats/satellite.py
bsk_rl/scene/__init__.py
bsk_rl/scene/rso_points.py
bsk_rl/scene/scenario.py
bsk_rl/scene/targets.py
bsk_rl/sim/__init__.py
bsk_rl/sim/simulator.py
bsk_rl/sim/world.py
bsk_rl/sim/dyn/__init__.py
bsk_rl/sim/dyn/base.py
bsk_rl/sim/dyn/ground_imaging.py
bsk_rl/sim/dyn/relative_motion.py
bsk_rl/sim/dyn/rso_inspection.py
bsk_rl/sim/fsw/__init__.py
bsk_rl/sim/fsw/base.py
bsk_rl/sim/fsw/ground_imaging.py
bsk_rl/sim/fsw/orbital.py
bsk_rl/sim/fsw/rso_inspection.py
bsk_rl/utils/__init__.py
bsk_rl/utils/actuator_primitives.py
bsk_rl/utils/attitude.py
bsk_rl/utils/functional.py
bsk_rl/utils/logging_config.py
bsk_rl/utils/orbital.py
bsk_rl/utils/vizard.py
bsk_rl/utils/rllib/__init__.py
bsk_rl/utils/rllib/callbacks.py
bsk_rl/utils/rllib/discounting.py
bsk_rl-1.2.15.dist-info/licenses/LICENSE
bsk_rl-1.2.15.dist-info/METADATA
bsk_rl-1.2.15.dist-info/WHEEL
bsk_rl-1.2.15.dist-info/top_level.txt
bsk_rl-1.2.15.dist-info/RECORD
