Metadata-Version: 2.4
Name: bsk_rl
Version: 1.2.15
Summary: RL environments and tools for spacecraft autonomy research, built on Basilisk. Developed by the AVS Lab.
Author-email: Mark Stephenson <mark.a.stephenson@colorado.edu>, Adam Herrmann <adam.herrmann@colorado.edu>
License: MIT
Requires-Python: >=3.10.0
License-File: LICENSE
Requires-Dist: bsk>=2.8.9
Requires-Dist: Deprecated
Requires-Dist: gymnasium
Requires-Dist: numpy
Requires-Dist: pandas
Requires-Dist: pettingzoo>=1.24.0
Requires-Dist: pytest==7.3.1
Requires-Dist: pytest-cov
Requires-Dist: pytest-repeat
Requires-Dist: pytest-retry
Requires-Dist: requests
Requires-Dist: ruff>=0.1.9
Requires-Dist: scipy
Provides-Extra: docs
Requires-Dist: ipykernel; extra == "docs"
Requires-Dist: ipywidgets; extra == "docs"
Requires-Dist: nbdime; extra == "docs"
Requires-Dist: nbsphinx; extra == "docs"
Requires-Dist: sphinx-rtd-theme; extra == "docs"
Requires-Dist: sphinxcontrib-youtube; extra == "docs"
Provides-Extra: rllib
Requires-Dist: dm_tree; extra == "rllib"
Requires-Dist: pyarrow; extra == "rllib"
Requires-Dist: ray[rllib]==2.35.0; extra == "rllib"
Requires-Dist: scikit-image; extra == "rllib"
Requires-Dist: torch; extra == "rllib"
Requires-Dist: typer; extra == "rllib"
Dynamic: license-file
